embetter/__init__.py
embetter/base.py
embetter/error.py
embetter/grab.py
embetter/utils.py
embetter/external/__init__.py
embetter/external/_cohere.py
embetter/external/_ollama.py
embetter/external/_openai.py
embetter/finetune/__init__.py
embetter/finetune/_constrastive_learn.py
embetter/finetune/_contrastive_tuner.py
embetter/finetune/_forward.py
embetter/finetune/_sbert_learn.py
embetter/model/__init__.py
embetter/model/_diff.py
embetter/multi/__init__.py
embetter/multi/_clip.py
embetter/text/__init__.py
embetter/text/_keras.py
embetter/text/_lite.py
embetter/text/_model2vec.py
embetter/text/_s2v.py
embetter/text/_sbert.py
embetter/text/_spacy.py
embetter/vision/__init__.py
embetter/vision/_colorhist.py
embetter/vision/_loader.py
embetter/vision/_torchvis.py
tests/__init__.py
tests/test_base.py
tests/test_docs.py
tests/test_text.py
tests/test_utils.py
tests/test_vision.py
embetter-0.8.0.dist-info/METADATA
embetter-0.8.0.dist-info/WHEEL
embetter-0.8.0.dist-info/top_level.txt
embetter-0.8.0.dist-info/RECORD
