Metadata-Version: 2.4
Name: embetter
Version: 0.8.0
Summary: Just a bunch of useful embeddings to get started quickly.
Home-page: https://koaning.github.io/embetter/
Author: Vincent D. Warmerdam
Project-URL: Documentation, https://koaning.github.io/embetter/
Project-URL: Source Code, https://github.com/koaning/embetter/
Project-URL: Issue Tracker, https://github.com/koaning/embetter/issues
Classifier: Intended Audience :: Science/Research
Classifier: Programming Language :: Python :: 3
Classifier: License :: OSI Approved :: MIT License
Classifier: Topic :: Scientific/Engineering
Classifier: Topic :: Scientific/Engineering :: Artificial Intelligence
Requires-Dist: scikit-learn>=1.0.0
Requires-Dist: pandas>=1.0.0
Requires-Dist: diskcache>=5.6.1
Requires-Dist: skops>=0.8.0
Requires-Dist: model2vec
Provides-Extra: sense2vec
Requires-Dist: sense2vec==2.0.0; extra == "sense2vec"
Requires-Dist: scikit-learn>=1.0.0; extra == "sense2vec"
Requires-Dist: pandas>=1.0.0; extra == "sense2vec"
Requires-Dist: diskcache>=5.6.1; extra == "sense2vec"
Requires-Dist: skops>=0.8.0; extra == "sense2vec"
Requires-Dist: model2vec; extra == "sense2vec"
Provides-Extra: sbert
Requires-Dist: sentence-transformers>=2.2.2; extra == "sbert"
Requires-Dist: scikit-learn>=1.0.0; extra == "sbert"
Requires-Dist: pandas>=1.0.0; extra == "sbert"
Requires-Dist: diskcache>=5.6.1; extra == "sbert"
Requires-Dist: skops>=0.8.0; extra == "sbert"
Requires-Dist: model2vec; extra == "sbert"
Provides-Extra: spacy
Requires-Dist: spacy>=3.5.0; extra == "spacy"
Requires-Dist: scikit-learn>=1.0.0; extra == "spacy"
Requires-Dist: pandas>=1.0.0; extra == "spacy"
Requires-Dist: diskcache>=5.6.1; extra == "spacy"
Requires-Dist: skops>=0.8.0; extra == "spacy"
Requires-Dist: model2vec; extra == "spacy"
Provides-Extra: text
Requires-Dist: sentence-transformers>=2.2.2; extra == "text"
Requires-Dist: sense2vec==2.0.0; extra == "text"
Requires-Dist: spacy>=3.5.0; extra == "text"
Requires-Dist: scikit-learn>=1.0.0; extra == "text"
Requires-Dist: pandas>=1.0.0; extra == "text"
Requires-Dist: diskcache>=5.6.1; extra == "text"
Requires-Dist: skops>=0.8.0; extra == "text"
Requires-Dist: model2vec; extra == "text"
Provides-Extra: vision
Requires-Dist: timm>=0.6.7; extra == "vision"
Requires-Dist: scikit-learn>=1.0.0; extra == "vision"
Requires-Dist: pandas>=1.0.0; extra == "vision"
Requires-Dist: diskcache>=5.6.1; extra == "vision"
Requires-Dist: skops>=0.8.0; extra == "vision"
Requires-Dist: model2vec; extra == "vision"
Provides-Extra: pytorch
Requires-Dist: torch>=1.12.0; extra == "pytorch"
Requires-Dist: scikit-learn>=1.0.0; extra == "pytorch"
Requires-Dist: pandas>=1.0.0; extra == "pytorch"
Requires-Dist: diskcache>=5.6.1; extra == "pytorch"
Requires-Dist: skops>=0.8.0; extra == "pytorch"
Requires-Dist: model2vec; extra == "pytorch"
Provides-Extra: openai
Requires-Dist: openai>=1.59.8; extra == "openai"
Requires-Dist: scikit-learn>=1.0.0; extra == "openai"
Requires-Dist: pandas>=1.0.0; extra == "openai"
Requires-Dist: diskcache>=5.6.1; extra == "openai"
Requires-Dist: skops>=0.8.0; extra == "openai"
Requires-Dist: model2vec; extra == "openai"
Provides-Extra: cohere
Requires-Dist: cohere>=4.11.2; extra == "cohere"
Requires-Dist: scikit-learn>=1.0.0; extra == "cohere"
Requires-Dist: pandas>=1.0.0; extra == "cohere"
Requires-Dist: diskcache>=5.6.1; extra == "cohere"
Requires-Dist: skops>=0.8.0; extra == "cohere"
Requires-Dist: model2vec; extra == "cohere"
Provides-Extra: ollama
Requires-Dist: ollama>=0.5.3; extra == "ollama"
Requires-Dist: scikit-learn>=1.0.0; extra == "ollama"
Requires-Dist: pandas>=1.0.0; extra == "ollama"
Requires-Dist: diskcache>=5.6.1; extra == "ollama"
Requires-Dist: skops>=0.8.0; extra == "ollama"
Requires-Dist: model2vec; extra == "ollama"
Provides-Extra: all
Requires-Dist: scikit-learn>=1.0.0; extra == "all"
Requires-Dist: pandas>=1.0.0; extra == "all"
Requires-Dist: diskcache>=5.6.1; extra == "all"
Requires-Dist: skops>=0.8.0; extra == "all"
Requires-Dist: model2vec; extra == "all"
Requires-Dist: sentence-transformers>=2.2.2; extra == "all"
Requires-Dist: sense2vec==2.0.0; extra == "all"
Requires-Dist: spacy>=3.5.0; extra == "all"
Requires-Dist: timm>=0.6.7; extra == "all"
Requires-Dist: openai>=1.59.8; extra == "all"
Provides-Extra: docs
Requires-Dist: mkdocs-material==9.6.9; extra == "docs"
Requires-Dist: mkdocstrings==0.29.0; extra == "docs"
Requires-Dist: mkdocstrings-python==1.16.0; extra == "docs"
Requires-Dist: mktestdocs==0.2.4; extra == "docs"
Provides-Extra: dev
Requires-Dist: scikit-learn>=1.0.0; extra == "dev"
Requires-Dist: pandas>=1.0.0; extra == "dev"
Requires-Dist: diskcache>=5.6.1; extra == "dev"
Requires-Dist: skops>=0.8.0; extra == "dev"
Requires-Dist: model2vec; extra == "dev"
Requires-Dist: sentence-transformers>=2.2.2; extra == "dev"
Requires-Dist: sense2vec==2.0.0; extra == "dev"
Requires-Dist: spacy>=3.5.0; extra == "dev"
Requires-Dist: timm>=0.6.7; extra == "dev"
Requires-Dist: openai>=1.59.8; extra == "dev"
Requires-Dist: mkdocs-material==9.6.9; extra == "dev"
Requires-Dist: mkdocstrings==0.29.0; extra == "dev"
Requires-Dist: mkdocstrings-python==1.16.0; extra == "dev"
Requires-Dist: mktestdocs==0.2.4; extra == "dev"
Requires-Dist: interrogate>=1.5.0; extra == "dev"
Requires-Dist: pytest>=4.0.2; extra == "dev"
Requires-Dist: ruff; extra == "dev"
Requires-Dist: pre-commit>=2.2.0; extra == "dev"
Requires-Dist: mktestdocs==0.2.4; extra == "dev"
Requires-Dist: datasets==2.8.0; extra == "dev"
Requires-Dist: pyarrow==20.0.0; extra == "dev"
Requires-Dist: matplotlib; extra == "dev"
Requires-Dist: pytest-xdist; extra == "dev"
Dynamic: author
Dynamic: classifier
Dynamic: description
Dynamic: description-content-type
Dynamic: home-page
Dynamic: project-url
Dynamic: provides-extra
Dynamic: requires-dist
Dynamic: summary
